selective_search/__init__.py
selective_search/core.py
selective_search/measure.py
selective_search/structure.py
selective_search/util.py
selective_search-1.1.0.dist-info/LICENSE
selective_search-1.1.0.dist-info/METADATA
selective_search-1.1.0.dist-info/WHEEL
selective_search-1.1.0.dist-info/top_level.txt
selective_search-1.1.0.dist-info/RECORD
